docs/conf.py
examples/run_boundprop.py
examples/run_lp_solver.py
examples/run_sdp_verify.py
jax_verify/__init__.py
jax_verify/sdp_verify.py
jax_verify/src/bound_propagation.py
jax_verify/src/crown_ibp.py
jax_verify/src/cvxpy_relaxation_solver.py
jax_verify/src/fastlin.py
jax_verify/src/ibp.py
jax_verify/src/intersection.py
jax_verify/src/relaxation.py
jax_verify/src/solve_relaxation.py
jax_verify/src/synthetic_primitives.py
jax_verify/src/utils.py
jax_verify/src/sdp_verify/crown_boundprop.py
jax_verify/src/sdp_verify/cvxpy_verify.py
jax_verify/src/sdp_verify/eigenvector_utils.py
jax_verify/src/sdp_verify/sdp_verify.py
jax_verify/src/sdp_verify/utils.py
jax_verify/tests/bound_propagation_test.py
jax_verify/tests/crownibp_test.py
jax_verify/tests/cvxpy_relaxation_test.py
jax_verify/tests/fastlin_test.py
jax_verify/tests/ibp_test.py
jax_verify/tests/model_zoo.py
jax_verify/tests/model_zoo_test.py
jax_verify/tests/sdp_verify/crown_boundprop_test.py
jax_verify/tests/sdp_verify/cvxpy_verify_test.py
jax_verify/tests/sdp_verify/sdp_verify_test.py
jax_verify/tests/sdp_verify/test_utilfuns.py
jax_verify/tests/sdp_verify/test_utils.py
jax_verify-1.0.dist-info/LICENSE
jax_verify-1.0.dist-info/METADATA
jax_verify-1.0.dist-info/WHEEL
jax_verify-1.0.dist-info/top_level.txt
jax_verify-1.0.dist-info/RECORD
