Metadata-Version: 2.1
Name: jax-verify
Version: 1.0
Summary: A library for neural network verification.
Home-page: https://github.com/deepmind/jax_verify
Author: DeepMind
Author-email: jax_verify@google.com
License: Apache 2.0
Platform: any
Requires-Dist: absl-py
Requires-Dist: cvxpy
Requires-Dist: dm-tree
Requires-Dist: jax (>=0.1.71)
Requires-Dist: jaxlib (>=0.1.49)
Requires-Dist: numpy
Requires-Dist: optax
Requires-Dist: dm-haiku
